cosdata/__init__.py
cosdata/embedding.py
cosdata/api/__init__.py
cosdata/api/auth.py
cosdata/api/client.py
cosdata/api/collections.py
cosdata/api/indexes.py
cosdata/api/search.py
cosdata/api/transactions.py
cosdata/api/vectors.py
cosdata/api/versions.py
cosdata_sdk-0.2.5.data/data/cosdata_client/__init__.py
cosdata_sdk-0.2.5.data/data/cosdata_client/embedding.py
cosdata_sdk-0.2.5.data/data/cosdata_client/api/__init__.py
cosdata_sdk-0.2.5.data/data/cosdata_client/api/auth.py
cosdata_sdk-0.2.5.data/data/cosdata_client/api/client.py
cosdata_sdk-0.2.5.data/data/cosdata_client/api/collections.py
cosdata_sdk-0.2.5.data/data/cosdata_client/api/indexes.py
cosdata_sdk-0.2.5.data/data/cosdata_client/api/search.py
cosdata_sdk-0.2.5.data/data/cosdata_client/api/transactions.py
cosdata_sdk-0.2.5.data/data/cosdata_client/api/vectors.py
cosdata_sdk-0.2.5.data/data/cosdata_client/api/versions.py
cosdata_sdk-0.2.5.dist-info/METADATA
cosdata_sdk-0.2.5.dist-info/WHEEL
cosdata_sdk-0.2.5.dist-info/licenses/LICENSE
cosdata_sdk-0.2.5.dist-info/RECORD
