Metadata-Version: 2.4
Name: cosdata-sdk
Version: 0.2.5
Summary: A Python SDK for interacting with the Cosdata Vector Database
Project-URL: Homepage, https://github.com/cosdata/cosdata-sdk-python
Project-URL: Repository, https://github.com/cosdata/cosdata-sdk-python.git
Project-URL: Issues, https://github.com/cosdata/cosdata-sdk-python/issues
Author-email: Cosdata <contact@cosdata.com>
License-Expression: MIT
License-File: LICENSE
Keywords: cosdata,database,embeddings,similarity-search,vector
Classifier: Development Status :: 3 - Alpha
Classifier: Intended Audience :: Developers
Classifier: License :: OSI Approved :: MIT License
Classifier: Programming Language :: Python :: 3
Classifier: Programming Language :: Python :: 3.8
Classifier: Programming Language :: Python :: 3.9
Classifier: Programming Language :: Python :: 3.10
Classifier: Programming Language :: Python :: 3.11
Classifier: Topic :: Software Development :: Libraries :: Python Modules
Requires-Python: >=3.9
Requires-Dist: cosdata-fastembed
Requires-Dist: datasets>=3.1.0
Requires-Dist: dotenv>=0.9.9
Requires-Dist: numpy>=1.24.4
Requires-Dist: pandas>=2.0.3
Requires-Dist: psutil>=7.0.0
Requires-Dist: requests>=2.32.4
